[{"stub":"She is a Conservative MP who comes from a white working class background.","constituency":"She is from your constituency.","personalization":"She frequently speaks out and votes against her party leadership.","substantive":"She opposes the construction of thousands of new onshore wind turbines.","justification":"In political debates, she regularly explains how her decisions help to promote the national interest.","responsiveness":"Asked recently about the role and duties of politicians, she said:  “Elections are important because they force me as a politician to listen and respond to the views of voters.”","gender":"female","party":"Conservative","class":"working","race":"white","text":"She is a Conservative MP who comes from a white working class background. She is from your constituency. She frequently speaks out and votes against her party leadership. She opposes the construction of thousands of new onshore wind turbines. In political debates, she regularly explains how her decisions help to promote the national interest. Asked recently about the role and duties of politicians, she said:  “Elections are important because they force me as a politician to listen and respond to the views of voters.”","PrimaryEmail":"159@email.com"}]
