[{"stub":"He is a Labour MP who comes from a white middle class background.","constituency":"He is from your constituency.","personalization":"He rarely speaks out and votes against his party leadership.","substantive":"He supports the building of the new HS2 railway between major UK cities.","justification":"In political debates, he regularly emphasises the benefits of his political positions for society as a whole.","responsiveness":"Asked recently about the role and duties of politicians, he said: “I went into politics to implement good ideas, not popular ones that win elections.”","gender":"male","party":"Labour","class":"middle","race":"white","text":"He is a Labour MP who comes from a white middle class background. He is from your constituency. He rarely speaks out and votes against his party leadership. He supports the building of the new HS2 railway between major UK cities. In political debates, he regularly emphasises the benefits of his political positions for society as a whole. Asked recently about the role and duties of politicians, he said: “I went into politics to implement good ideas, not popular ones that win elections.”","PrimaryEmail":"55@email.com"}]
